{
  "tabSrc": "https://amazingandyyy.com/ukulake/ukejams.com/library/Dollar Short of Happy, A.pdf",
  "source": "ukejams.com",
  "originalSrc": "https://drive.google.com/uc?export=download&id=1FJ1wu6BZ-1yoGLy0HcMt-xS0lFLWDVDM",
  "title": "Dollar Short of Happy, A",
  "labels": [
    "ukejams"
  ],
  "additionalData": {
    "genre": "2010s",
    "audioUrl": "https://drive.google.com/file/d/1zXI0AcCWoh490l6B-kGeggBm0Jw7RzP3",
    "artist": "Nick Lowe",
    "videoUrl": "https://youtu.be/zjZIFTxKHGw"
  }
}